sky_fall-0.2.0.dist-info/licenses/LICENSE
skyfall/__init__.py
skyfall/client.py
sky_fall-0.2.0.dist-info/METADATA
sky_fall-0.2.0.dist-info/WHEEL
sky_fall-0.2.0.dist-info/top_level.txt
sky_fall-0.2.0.dist-info/RECORD
