Metadata-Version: 2.4
Name: sky-fall
Version: 0.2.0
Summary: Lightweight client for fetching current weather from OpenWeatherMap.
Author: Superintendent
License: MIT License
Project-URL: Homepage, https://github.com/superintendent2521/sky-fall
Project-URL: Documentation, https://github.com/superintendent2521/sky-fall#readme
Keywords: weather,openweathermap,api,client
Classifier: Programming Language :: Python :: 3
Classifier: Programming Language :: Python :: 3 :: Only
Classifier: Programming Language :: Python :: 3.8
Classifier: Programming Language :: Python :: 3.9
Classifier: Programming Language :: Python :: 3.10
Classifier: Programming Language :: Python :: 3.11
Classifier: License :: OSI Approved :: MIT License
Classifier: Operating System :: OS Independent
Classifier: Intended Audience :: Developers
Classifier: Topic :: Software Development :: Libraries :: Python Modules
Classifier: Topic :: Internet :: WWW/HTTP
Requires-Python: >=3.8
License-File: LICENSE
Requires-Dist: requests<3.0.0,>=2.31.0
Dynamic: license-file
